r2e_test_server/ast/__init__.py
r2e_test_server/ast/transformer.py
r2e_test_server/cli.py
r2e_test_server/instrument/__init__.py
r2e_test_server/instrument/arguments.py
r2e_test_server/instrument/base.py
r2e_test_server/modules/__init__.py
r2e_test_server/modules/explorer.py
r2e_test_server/server.py
r2e_test_server/testing/cleaner.py
r2e_test_server/testing/codecov.py
r2e_test_server/testing/loader.py
r2e_test_server/testing/r2e_testprogram.py
r2e_test_server/testing/result.py
r2e_test_server/testing/runner.py
r2e_test_server-0.1.8.dist-info/LICENSE
r2e_test_server-0.1.8.dist-info/METADATA
r2e_test_server-0.1.8.dist-info/WHEEL
r2e_test_server-0.1.8.dist-info/entry_points.txt
r2e_test_server-0.1.8.dist-info/RECORD
