Metadata-Version: 2.1
Name: r2e_test_server
Version: 0.1.8
Summary: Test Server For R2E
Home-page: https://github.com/r2e-project/r2e-test-server
License: MIT
Author: Naman Jain
Author-email: naman_jain@berkeley.com
Requires-Python: >=3.7,<4.0
Classifier: License :: OSI Approved :: MIT License
Classifier: Programming Language :: Python :: 3
Classifier: Programming Language :: Python :: 3.7
Classifier: Programming Language :: Python :: 3.8
Classifier: Programming Language :: Python :: 3.9
Classifier: Programming Language :: Python :: 3.10
Classifier: Programming Language :: Python :: 3.11
Classifier: Programming Language :: Python :: 3.12
Requires-Dist: astor (>=0.8.1,<0.9.0)
Requires-Dist: coverage (>=7,<8)
Requires-Dist: pyright (>=1.1.360,<2.0.0)
Requires-Dist: rpyc (>=6.0.0,<7.0.0)
Requires-Dist: typer (>=0.12.3,<0.13.0)
Project-URL: Repository, https://github.com/r2e-project/r2e-test-server
